promptml_cli/__about__.py
promptml_cli/__init__.py
promptml_cli/client.py
promptml_cli/generation.py
promptml_cli/main.py
promptml_cli-1.0.1.dist-info/METADATA
promptml_cli-1.0.1.dist-info/WHEEL
promptml_cli-1.0.1.dist-info/entry_points.txt
promptml_cli-1.0.1.dist-info/licenses/LICENSE
promptml_cli-1.0.1.dist-info/RECORD
