Metadata-Version: 2.3
Name: promptml-cli
Version: 1.0.1
Summary: A CLI tool to run PromptML scripts
Project-URL: Documentation, https://github.com/narenaryan/promptml-cli/blob/main/README.md
Project-URL: Issues, https://github.com/narenaryan/promptml-cli/issues
Project-URL: Source, https://github.com/narenaryan/promptml-cli/
Author-email: "Vidura Labs Inc." <contact@vidura.ai>, Naren Yellavula <naren.yellavula@gmail.com>
License-Expression: MIT
License-File: LICENSE
Keywords: artificial-intelligence,dsl,generative-ai,language,prompt-engineering,promptml,promptml-cli
Classifier: Development Status :: 4 - Beta
Classifier: Programming Language :: Python
Classifier: Programming Language :: Python :: 3.8
Classifier: Programming Language :: Python :: 3.9
Classifier: Programming Language :: Python :: 3.10
Classifier: Programming Language :: Python :: 3.11
Classifier: Programming Language :: Python :: 3.12
Classifier: Programming Language :: Python :: Implementation :: CPython
Classifier: Programming Language :: Python :: Implementation :: PyPy
Requires-Python: >=3.8
Requires-Dist: click==8.1.7
Requires-Dist: google-generativeai==0.6.0
Requires-Dist: openai==1.33.0
Requires-Dist: promptml==0.6.1
Requires-Dist: rich==13.7.1
